{
    "Ar36": {
        "error": 0.00029942021397327909, 
        "fit": "linear", 
        "value": 0.014701057362888995
    }, 
    "Ar37": {
        "error": 0.023720403967023216, 
        "fit": "linear", 
        "value": 0.35602666588354431
    }, 
    "Ar38": {
        "error": 0.032089633158078688, 
        "fit": "linear", 
        "value": 2.3959501385853792
    }, 
    "Ar39": {
        "error": 0.027160413609644149, 
        "fit": "linear", 
        "value": 202.14810221193278
    }, 
    "Ar40": {
        "error": 0.1005553326314368, 
        "fit": "linear", 
        "value": 1703.1173776333267
    }, 
    "Ar41": {
        "error": 0.010612917017535405, 
        "fit": "average", 
        "value": -0.00974937407222266
    }
}