{
    "Ar36": {
        "error": 0.00038404203597978791, 
        "fit": "linear", 
        "value": 0.021722697326842375
    }, 
    "Ar37": {
        "error": 0.024596705607878862, 
        "fit": "linear", 
        "value": 0.50007822232150456
    }, 
    "Ar38": {
        "error": 0.023590590665787333, 
        "fit": "linear", 
        "value": 2.8566473698906183
    }, 
    "Ar39": {
        "error": 0.029671519634502222, 
        "fit": "linear", 
        "value": 244.23088506341219
    }, 
    "Ar40": {
        "error": 0.11672330333237313, 
        "fit": "linear", 
        "value": 2073.6528769710399
    }, 
    "Ar41": {
        "error": 0.010300820157293661, 
        "fit": "average", 
        "value": -0.012608437950705896
    }
}