{
    "Ar36": {
        "error": 0.00024355596808446102, 
        "fit": "linear", 
        "value": 0.0064431467893825718
    }, 
    "Ar37": {
        "error": 0.022641802869005512, 
        "fit": "linear", 
        "value": 0.19674787663673565
    }, 
    "Ar38": {
        "error": 0.041083460659016455, 
        "fit": "linear", 
        "value": 1.3250339706669219
    }, 
    "Ar39": {
        "error": 0.019940371013339012, 
        "fit": "linear", 
        "value": 102.05133841614492
    }, 
    "Ar40": {
        "error": 0.074385302272410636, 
        "fit": "linear", 
        "value": 865.69775435796782
    }, 
    "Ar41": {
        "error": 0.011139162854852556, 
        "fit": "average", 
        "value": -0.0011848993164797624
    }
}