{
    "AX": {
        "error": 0.005096505010153421, 
        "fit": "average", 
        "value": -0.01088249464195946
    }, 
    "CDD": {
        "error": 4.964382813807877e-06, 
        "fit": "average", 
        "value": 1.1884091266741355e-05
    }, 
    "H1": {
        "error": 0.013234347503207679, 
        "fit": "average", 
        "value": -0.008028731843741197
    }, 
    "H2": {
        "error": 0.013199540163395859, 
        "fit": "average", 
        "value": -0.06671029015237259
    }, 
    "L1": {
        "error": 0.015857379551059213, 
        "fit": "average", 
        "value": -0.19808516902137652
    }, 
    "L2": {
        "error": 0.014900028951511435, 
        "fit": "average", 
        "value": 0.10037512560375035
    }
}