{
    "AX": {
        "error": 0.01136766057632467, 
        "fit": "average", 
        "value": -0.02342864176614381
    }, 
    "CDD": {
        "error": 1.1752559344352443e-05, 
        "fit": "average", 
        "value": 9.337500281011064e-05
    }, 
    "H1": {
        "error": 0.011469118215888483, 
        "fit": "average", 
        "value": 0.037740672504978964
    }, 
    "H2": {
        "error": 0.01389053068069069, 
        "fit": "average", 
        "value": -0.10898629083503904
    }, 
    "L1": {
        "error": 0.014527207699384639, 
        "fit": "average", 
        "value": -0.02997221232258848
    }, 
    "L2": {
        "error": 0.011388304436863507, 
        "fit": "average", 
        "value": -0.041182814505829037
    }
}