{
    "Ar36": {
        "error": 0.00020559249300667549, 
        "fit": "linear", 
        "value": 0.0049174013308276743
    }, 
    "Ar37": {
        "error": 0.022054973191952883, 
        "fit": "linear", 
        "value": 0.35195242146691597
    }, 
    "Ar38": {
        "error": 0.034440792542041465, 
        "fit": "linear", 
        "value": 1.7393301187194581
    }, 
    "Ar39": {
        "error": 0.023427396193222361, 
        "fit": "linear", 
        "value": 156.82374880219407
    }, 
    "Ar40": {
        "error": 0.081797296426524488, 
        "fit": "linear", 
        "value": 1314.4441260886342
    }, 
    "Ar41": {
        "error": 0.012051336075248434, 
        "fit": "average", 
        "value": 0.26470974732190372
    }
}