{
    "AX": {
        "error": 0.005016159344231317, 
        "fit": "average", 
        "value": -0.0015348715140135027
    }, 
    "CDD": {
        "error": 1.4464211808293488e-05, 
        "fit": "average", 
        "value": 0.00018080795998685062
    }, 
    "H1": {
        "error": 0.012812913736678096, 
        "fit": "average", 
        "value": 0.024387132019425432
    }, 
    "H2": {
        "error": 0.010893818124682956, 
        "fit": "average", 
        "value": -0.05184515132132219
    }, 
    "L1": {
        "error": 0.015749200955265514, 
        "fit": "average", 
        "value": -0.1722196061758344
    }, 
    "L2": {
        "error": 0.012437350376929168, 
        "fit": "average", 
        "value": 0.11994338511916187
    }
}