{
    "AX": {
        "error": 0.004507744433100419, 
        "fit": "average", 
        "value": 0.002004123036628395
    }, 
    "CDD": {
        "error": 1.52634875327361e-05, 
        "fit": "average", 
        "value": 0.00019099432392977178
    }, 
    "H1": {
        "error": 0.012516724971404438, 
        "fit": "average", 
        "value": 0.039547521853334426
    }, 
    "H2": {
        "error": 0.010644877246129838, 
        "fit": "average", 
        "value": 0.20657006137771533
    }, 
    "L1": {
        "error": 0.014330349719341794, 
        "fit": "average", 
        "value": -0.16685096762424412
    }, 
    "L2": {
        "error": 0.012206515860607649, 
        "fit": "average", 
        "value": 0.08778328630529965
    }
}