{
    "AX": {
        "error": 0.005566380448221754, 
        "fit": "average", 
        "value": -0.007585520988019804
    }, 
    "CDD": {
        "error": 1.4465624627917707e-05, 
        "fit": "average", 
        "value": 0.0001769880735082552
    }, 
    "H1": {
        "error": 0.010882323050376069, 
        "fit": "average", 
        "value": 0.05389481239641706
    }, 
    "H2": {
        "error": 0.01224055631942769, 
        "fit": "average", 
        "value": -0.016873732649643595
    }, 
    "L1": {
        "error": 0.015362430964379324, 
        "fit": "average", 
        "value": -0.16187133627342215
    }, 
    "L2": {
        "error": 0.012295100725999167, 
        "fit": "average", 
        "value": 0.011130397374533156
    }
}