{
    "AX": {
        "error": 0.008599625835422607, 
        "fit": "average", 
        "value": -0.004292397104533544
    }, 
    "CDD": {
        "error": 1.3451005758328942e-05, 
        "fit": "average", 
        "value": 0.00017826136900112033
    }, 
    "H1": {
        "error": 0.011207382526664228, 
        "fit": "average", 
        "value": -0.024178559808448578
    }, 
    "H2": {
        "error": 0.011279915905394636, 
        "fit": "average", 
        "value": 0.15816554820048623
    }, 
    "L1": {
        "error": 0.01162382687352972, 
        "fit": "average", 
        "value": -0.21593264926535388
    }, 
    "L2": {
        "error": 0.012419695473941797, 
        "fit": "average", 
        "value": -0.0956858928331106
    }
}