{
    "AX": {
        "error": 0.005147527748036269, 
        "fit": "average", 
        "value": 0.009693165864155162
    }, 
    "CDD": {
        "error": 2.1868010780972214e-06, 
        "fit": "average", 
        "value": 3.819886478595435e-06
    }, 
    "H1": {
        "error": 0.012540686878436527, 
        "fit": "average", 
        "value": -0.017747974736024238
    }, 
    "H2": {
        "error": 0.010968851227999944, 
        "fit": "average", 
        "value": -0.06997879336364955
    }, 
    "L1": {
        "error": 0.014218610854586493, 
        "fit": "average", 
        "value": -0.17819298230460845
    }, 
    "L2": {
        "error": 0.011146914044637801, 
        "fit": "average", 
        "value": 0.10348062464036048
    }
}