{
    "AX": {
        "error": 0.008808757280627843, 
        "fit": "average", 
        "value": -0.029418373037125484
    }, 
    "CDD": {
        "error": 1.2732954928651456e-06, 
        "fit": "average", 
        "value": 1.2732954928651452e-06
    }, 
    "H1": {
        "error": 0.00893351356227601, 
        "fit": "average", 
        "value": 0.0112507936041967
    }, 
    "H2": {
        "error": 0.010251248059199261, 
        "fit": "average", 
        "value": -0.07616092747623991
    }, 
    "L1": {
        "error": 0.021554525170170907, 
        "fit": "average", 
        "value": -0.1335024743658041
    }, 
    "L2": {
        "error": 0.009822869810569809, 
        "fit": "average", 
        "value": -0.03539100931704287
    }
}