{
    "AX": {
        "error": 0.006045091599160488, 
        "fit": "average", 
        "value": 0.005439219955911135
    }, 
    "CDD": {
        "error": 1.8685402531207105e-05, 
        "fit": "average", 
        "value": 0.00018165682364876072
    }, 
    "H1": {
        "error": 0.014510193615204486, 
        "fit": "average", 
        "value": 0.021214238221808852
    }, 
    "H2": {
        "error": 0.012769817392893434, 
        "fit": "average", 
        "value": -0.06803882271827509
    }, 
    "L1": {
        "error": 0.018221569284738903, 
        "fit": "average", 
        "value": -0.1899645143835288
    }, 
    "L2": {
        "error": 0.01293574377940224, 
        "fit": "average", 
        "value": -0.03935218086310973
    }
}