{
    "AX": {
        "error": 0.006444416959563917, 
        "fit": "average", 
        "value": 0.0013918652820090452
    }, 
    "CDD": {
        "error": 1.5684309840250446e-05, 
        "fit": "average", 
        "value": 0.0001324227312579751
    }, 
    "H1": {
        "error": 0.013680568811976762, 
        "fit": "average", 
        "value": 0.024920426840091953
    }, 
    "H2": {
        "error": 0.012953629111486053, 
        "fit": "average", 
        "value": -0.060963901817902094
    }, 
    "L1": {
        "error": 0.01895747918193889, 
        "fit": "average", 
        "value": -0.19304580312843125
    }, 
    "L2": {
        "error": 0.015001675269038041, 
        "fit": "average", 
        "value": -0.003908036825143629
    }
}