{
    "AX": {
        "error": 0.0057158578553527664, 
        "fit": "average", 
        "value": 0.004917496515231
    }, 
    "CDD": {
        "error": 1.4526583101704096e-05, 
        "fit": "average", 
        "value": 0.0001324227312579751
    }, 
    "H1": {
        "error": 0.013035386422939384, 
        "fit": "average", 
        "value": 0.04126514852331537
    }, 
    "H2": {
        "error": 0.013228814765439878, 
        "fit": "average", 
        "value": -0.06602842439768009
    }, 
    "L1": {
        "error": 0.017167074638081446, 
        "fit": "average", 
        "value": -0.19017610383194147
    }, 
    "L2": {
        "error": 0.013766763391292245, 
        "fit": "average", 
        "value": 0.07660703752319226
    }
}