{
    "AX": {
        "error": 0.006229767578291593, 
        "fit": "average", 
        "value": 0.0033661854314333242
    }, 
    "CDD": {
        "error": 1.4465145472348085e-05, 
        "fit": "average", 
        "value": 0.00012393409463887413
    }, 
    "H1": {
        "error": 0.012722101807031618, 
        "fit": "average", 
        "value": 0.03324762255263825
    }, 
    "H2": {
        "error": 0.013587301017898262, 
        "fit": "average", 
        "value": -0.04302013940436559
    }, 
    "L1": {
        "error": 0.018535800628567193, 
        "fit": "average", 
        "value": -0.17080282589627638
    }, 
    "L2": {
        "error": 0.014225122583063849, 
        "fit": "average", 
        "value": 0.16428725845697853
    }
}