{
    "AX": {
        "error": 0.0070736638084426375, 
        "fit": "average", 
        "value": -0.0036140409801566206
    }, 
    "CDD": {
        "error": 1.995282709574988e-05, 
        "fit": "average", 
        "value": 0.000195488308022237
    }, 
    "H1": {
        "error": 0.01749051504588181, 
        "fit": "average", 
        "value": 0.01707423185957048
    }, 
    "H2": {
        "error": 0.015961903155528555, 
        "fit": "average", 
        "value": 0.19617507611666737
    }, 
    "L1": {
        "error": 0.019340567618414947, 
        "fit": "average", 
        "value": -0.21847966648912168
    }, 
    "L2": {
        "error": 0.015010203959299662, 
        "fit": "average", 
        "value": 0.09367016040350255
    }
}