{
    "AX": {
        "error": 0.00523797722931968, 
        "fit": "average", 
        "value": 0.014689614110344943
    }, 
    "CDD": {
        "error": 1.4660681871083634e-05, 
        "fit": "average", 
        "value": 0.00016298182308673858
    }, 
    "H1": {
        "error": 0.011720598118708122, 
        "fit": "average", 
        "value": 0.0011657903417168806
    }, 
    "H2": {
        "error": 0.01030296226865231, 
        "fit": "average", 
        "value": 0.2500552057288587
    }, 
    "L1": {
        "error": 0.018119755133279365, 
        "fit": "average", 
        "value": -0.001085763633212385
    }, 
    "L2": {
        "error": 0.011505802533504313, 
        "fit": "average", 
        "value": -0.10867131019864852
    }
}