{
    "Ar36": {
        "error": 0.00019735895826884366, 
        "fit": "parabolic", 
        "value": 0.0049131916955004818
    }, 
    "Ar37": {
        "error": 0.014346677965441203, 
        "fit": "linear", 
        "value": -0.11771335779512947
    }, 
    "Ar38": {
        "error": 0.023168105764227603, 
        "fit": "linear", 
        "value": -0.045631679359085575
    }, 
    "Ar39": {
        "error": 0.010660349276339159, 
        "fit": "parabolic", 
        "value": 0.064499979112705441
    }, 
    "Ar40": {
        "error": 0.024006677817854826, 
        "fit": "parabolic", 
        "value": 1.2159049388720793
    }, 
    "Ar41": {
        "error": 0.0059745447021263198, 
        "fit": "average", 
        "value": -0.038780394850400628
    }
}